LICENSE
MANIFEST.in
README.rst
setup.cfg
setup.py
komoog/__init__.py
komoog/audio.py
komoog/gpx.py
komoog/io.py
komoog/komoot.py
komoog/metadata.py
komoog/paths.py
komoog/plot.py
komoog.egg-info/PKG-INFO
komoog.egg-info/SOURCES.txt
komoog.egg-info/dependency_links.txt
komoog.egg-info/not-zip-safe
komoog.egg-info/requires.txt
komoog.egg-info/top_level.txt
komoog/tests/__init__.py
komoog/tests/gpx_tests.py