Metadata-Version: 1.2
Name: komoog
Version: 0.0.4
Summary: Convert komoot hiking trips to sounds.
Home-page: https://github.com/benmaier/komoog
Author: Benjamin F. Maier
Author-email: contact@benmaier.org
License: MIT
Project-URL: Documentation, http://komoog.readthedocs.io
Project-URL: Contributing Statement, https://github.com/benmaier/komoog/blob/master/CONTRIBUTING.md
Project-URL: Bug Reports, https://github.com/benmaier/komoog/issues
Project-URL: Source, https://github.com/benmaier/komoog/
Project-URL: PyPI, https://pypi.org/project/komoog/
Platform: UNKNOWN
Classifier: License :: OSI Approved :: MIT License
Classifier: Programming Language :: Python :: 3.6
Classifier: Programming Language :: Python :: 3.7
Classifier: Programming Language :: Python :: 3.8
Requires-Python: >=3.6
